ppocronnx/__init__.py
ppocronnx/demo.py
ppocronnx/predict_system.py
ppocronnx/utility.py
ppocronnx/cls/__init__.py
ppocronnx/cls/postprocess.py
ppocronnx/cls/predict_cls.py
ppocronnx/det/__init__.py
ppocronnx/det/postprocess.py
ppocronnx/det/predict_det.py
ppocronnx/det/preprocess.py
ppocronnx/model/ch_PP-OCRv2_rec_infer.onnx
ppocronnx/model/ch_PP-OCRv3_det_infer.onnx
ppocronnx/model/cls-model.onnx
ppocronnx/model/ppocr_keys_v1.txt
ppocronnx/rec/__init__.py
ppocronnx/rec/predict_rec.py
ppocronnx/rec/rec_decoder.py
ppocr_onnx-0.0.3.9.dist-info/LICENSE
ppocr_onnx-0.0.3.9.dist-info/METADATA
ppocr_onnx-0.0.3.9.dist-info/WHEEL
ppocr_onnx-0.0.3.9.dist-info/top_level.txt
ppocr_onnx-0.0.3.9.dist-info/RECORD
